midi_parse/__init__.py
midi_parse/__main__.py
midi_parse/midi_parse.py
midi_parse-0.0.8.dist-info/LICENSE
midi_parse-0.0.8.dist-info/METADATA
midi_parse-0.0.8.dist-info/WHEEL
midi_parse-0.0.8.dist-info/top_level.txt
midi_parse-0.0.8.dist-info/RECORD
